aws_analytics_reference_architecture/__init__.py
aws_analytics_reference_architecture/py.typed
aws_analytics_reference_architecture/_jsii/__init__.py
aws_analytics_reference_architecture/_jsii/aws-analytics-reference-architecture@2.12.13.jsii.tgz
aws_analytics_reference_architecture-2.12.13.dist-info/LICENSE
aws_analytics_reference_architecture-2.12.13.dist-info/METADATA
aws_analytics_reference_architecture-2.12.13.dist-info/WHEEL
aws_analytics_reference_architecture-2.12.13.dist-info/top_level.txt
aws_analytics_reference_architecture-2.12.13.dist-info/RECORD
