Metadata-Version: 2.1
Name: aws_analytics_reference_architecture
Version: 2.12.13
Summary: aws-analytics-reference-architecture
Home-page: https://aws-samples.github.io/aws-analytics-reference-architecture/
Author: Amazon Web Services
License: MIT-0
Project-URL: Source, https://github.com/aws-samples/aws-analytics-reference-architecture.git
Classifier: Intended Audience :: Developers
Classifier: Operating System :: OS Independent
Classifier: Programming Language :: JavaScript
Classifier: Programming Language :: Python :: 3 :: Only
Classifier: Programming Language :: Python :: 3.8
Classifier: Programming Language :: Python :: 3.9
Classifier: Programming Language :: Python :: 3.10
Classifier: Programming Language :: Python :: 3.11
Classifier: Typing :: Typed
Classifier: Development Status :: 4 - Beta
Classifier: License :: OSI Approved
Requires-Python: ~=3.8
License-File: LICENSE
Requires-Dist: aws-cdk-lib ==2.130.0
Requires-Dist: aws-cdk.aws-glue-alpha ==2.130.0.a0
Requires-Dist: aws-cdk.aws-redshift-alpha ==2.130.0.a0
Requires-Dist: constructs <11.0.0,>=10.3.0
Requires-Dist: jsii <2.0.0,>=1.94.0
Requires-Dist: publication >=0.0.3
Requires-Dist: typeguard ~=2.13.3
